closelove/__init__.py
closelove/captcha.py
closelove/closelove.py
closelove/web_socket.py
closelove-1.9.dist-info/METADATA
closelove-1.9.dist-info/WHEEL
closelove-1.9.dist-info/top_level.txt
closelove-1.9.dist-info/RECORD
