Metadata-Version: 2.4
Name: closelove
Version: 1.9
Summary: A simple library for Android UI automation using UIAutomator and ADB
Home-page: https://pypi.org/project/closelove/
Author: CodeMaster
Author-email: theloveme401@gmail.com
Classifier: Programming Language :: Python :: 3
Classifier: License :: OSI Approved :: MIT License
Classifier: Operating System :: OS Independent
Requires-Python: >=3.6
Requires-Dist: uiautomator
Requires-Dist: pydub
Requires-Dist: phonenumbers
Requires-Dist: selenium
Requires-Dist: seleniumbase
Requires-Dist: requests
Requires-Dist: pycountry
Requires-Dist: numpy
Requires-Dist: Pillow
Requires-Dist: SpeechRecognition
Requires-Dist: names
Requires-Dist: websocket-client
Dynamic: author
Dynamic: author-email
Dynamic: classifier
Dynamic: description
Dynamic: description-content-type
Dynamic: home-page
Dynamic: requires-dist
Dynamic: requires-python
Dynamic: summary
